redis_ao/__init__.py
redis_ao/version.py
redis_ao/infrastructure/__init__.py
redis_ao/infrastructure/ao.py
redis_ao/infrastructure/do.py
redis_ao-0.1.1.dist-info/LICENSE
redis_ao-0.1.1.dist-info/METADATA
redis_ao-0.1.1.dist-info/WHEEL
redis_ao-0.1.1.dist-info/top_level.txt
redis_ao-0.1.1.dist-info/RECORD
