Metadata-Version: 2.1
Name: redis-ao
Version: 0.1.1
Summary: Exposed interface for accessing k3s controller
Author: wangziling100
Author-email: wangziling100@163.com
Classifier: Programming Language :: Python :: 3
Classifier: License :: OSI Approved :: MIT License
License-File: LICENSE
